semver.py
semver-2.12.0.dist-info/LICENSE.txt
semver-2.12.0.dist-info/METADATA
semver-2.12.0.dist-info/WHEEL
semver-2.12.0.dist-info/entry_points.txt
semver-2.12.0.dist-info/top_level.txt
semver-2.12.0.dist-info/RECORD
