Metadata-Version: 2.1
Name: semver
Version: 2.12.0
Summary: Python helper for Semantic Versioning (http://semver.org/)
Home-page: https://github.com/python-semver/python-semver
Author: Kostiantyn Rybnikov
Author-email: k-bx@k-bx.com
License: BSD
Download-URL: https://github.com/python-semver/python-semver/downloads
Project-URL: Documentation, https://python-semver.rtfd.io
Project-URL: Releases, https://github.com/python-semver/python-semver/releases
Project-URL: Bug Tracker, https://github.com/python-semver/python-semver/issues
Platform: UNKNOWN
Classifier: Environment :: Web Environment
Classifier: Intended Audience :: Developers
Classifier: License :: OSI Approved :: BSD License
Classifier: Operating System :: OS Independent
Classifier: Programming Language :: Python
Classifier: Programming Language :: Python :: 2
Classifier: Programming Language :: Python :: 2.7
Classifier: Programming Language :: Python :: 3
Classifier: Programming Language :: Python :: 3.4
Classifier: Programming Language :: Python :: 3.5
Classifier: Programming Language :: Python :: 3.6
Classifier: Programming Language :: Python :: 3.7
Classifier: Topic :: Software Development :: Libraries :: Python Modules
Requires-Python: >=2.7, !=3.0.*, !=3.1.*, !=3.2.*, !=3.3.*
